<?xml version="1.0" encoding="utf-8" ?>
<l:locale lang="cs"
  xmlns:l="http://docbook2x.sourceforge.net/xsl/localization"
  xmlns:dl="http://docbook2x.sourceforge.net/xsl/document-localization"
  >

  <l:locale-info>
    <l:english-language-name>Czech</l:english-language-name>
  </l:locale-info>

  <dl:title element="abstract">Abstrakt</dl:title>
  <dl:label element="answer">Odpověď:</dl:label>
  <dl:title element="appendix">Příloha</dl:title>
  <dl:title element="article">Článek</dl:title>
  <dl:title element="bibliography">Bibliografie</dl:title>
  <dl:title element="book">Kniha</dl:title>
  <dl:title element="caution">Výstraha</dl:title>
  <dl:title element="chapter">Kapitola</dl:title>
  <dl:title element="colophon">Tiráž</dl:title>
  <dl:title element="copyright">Copyright</dl:title>
  <dl:title element="dedication">Věnování</dl:title>
  <dl:title element="edition">Vydání</dl:title>
  <dl:title element="equation">Rovnice</dl:title>
  <dl:title element="example">Příklad</dl:title>
  <dl:title element="figure">Obrázek</dl:title>
  <dl:title element="glossary">Slovník</dl:title>
  <dl:title element="important">Důležité</dl:title>
  <dl:title element="isbn">ISBN</dl:title>
  <dl:title element="legalnotice">Právní doložka</dl:title>
  <dl:title element="msgaud">Publikum</dl:title>
  <dl:title element="msglevel">Úroveň</dl:title>
  <dl:title element="msgorig">Původ</dl:title>
  <dl:title element="note">Poznámka</dl:title>
  <dl:title element="part">Část</dl:title>
  <dl:title element="preface">Předmluva</dl:title>
  <dl:title element="procedure">Postup</dl:title>
  <dl:label element="question">Otázka:</dl:label>
  <dl:title element="reference">Odkaz</dl:title>
  <dl:title element="refnamediv">Jméno</dl:title>
  <dl:title element="refsynopsisdiv">Přehled</dl:title>
  <dl:title element="revhistory">Přehled revizí</dl:title>
  <dl:title element="revision">Revize</dl:title>
  <dl:title element="sect1">Oddíl</dl:title>
  <dl:title element="sect2">Oddíl</dl:title>
  <dl:title element="sect3">Oddíl</dl:title>
  <dl:title element="sect4">Oddíl</dl:title>
  <dl:title element="sect5">Oddíl</dl:title>
  <dl:title element="section">Oddíl</dl:title>
  <dl:rendering key="see">Viz <dl:content/></dl:rendering>
  <dl:rendering key="seealso">Viz též <dl:content/></dl:rendering>
  <dl:title element="set">Sada</dl:title>
  <dl:title element="setindex">Rejstřík sady</dl:title>
  <dl:title element="sidebar">Marginálie</dl:title>
  <dl:title element="step">krok</dl:title>
  <dl:title element="table">Tabulka</dl:title>
  <dl:title element="tip">Tip</dl:title>
  <dl:title element="warning">Varování</dl:title>
  <dl:text key="inline-list-separator">, </dl:text>
  <dl:text key="footnotes">Poznámky </dl:text>
  <dl:title element="tablenotes">Poznámky</dl:title>
  <dl:text key="List of Equations">Seznam rovnic</dl:text>
  <dl:text key="List of Examples">Seznam příkladů</dl:text>
  <dl:text key="List of Figures">Seznam obrázků</dl:text>
  <dl:text key="List of Tables">Seznam tabulek</dl:text>
  <dl:text key="List of Unknown">Seznam neznámého</dl:text>
  <dl:text key="lowercase-alphabet">aábcčdďeéěfghiíjklmnoópqrřsštťuúůvwxyýzž</dl:text>
  <dl:text key="uppercase-alphabet">AÁBCČDĎEÉĚFGHIÍJKLMNOÓPQRŘSŠTŤUÚŮVWXYÝZŽ</dl:text>
  <dl:text key="start-quote">„</dl:text>
  <dl:text key="end-quote">“</dl:text>
  <dl:text key="nested-start-quote">‚</dl:text>
  <dl:text key="nested-end-quote">‘</dl:text>
  <dl:text key="list-bullet">•</dl:text>
  <dl:rendering key="glosssee">Viz <dl:content/></dl:rendering>
  <dl:rendering key="glossseealso">Viz též <dl:content/></dl:rendering>
  <dl:label element="msgaud">Publikum: </dl:label>
  <dl:label element="msglevel">Úroveň: </dl:label>
  <dl:label element="msgorig">Původ: </dl:label>

  <!-- arg/group/cmdsynopsis decorations -->
  <dl:text key="arg-choice-opt-start">[</dl:text>
  <dl:text key="arg-choice-opt-end">]</dl:text>
  <dl:text key="arg-choice-req-start">{</dl:text>
  <dl:text key="arg-choice-req-end">}</dl:text>
  <dl:text key="arg-choice-plain-start"> </dl:text>
  <dl:text key="arg-choice-plain-end"> </dl:text>
  <dl:text key="arg-choice-default-start">[</dl:text>
  <dl:text key="arg-choice-default-end">]</dl:text>
  <dl:text key="arg-rep-repeat">…</dl:text>
  <dl:text key="a-rep-norepeat"></dl:text>
  <dl:text key="arg-or-separator"> | </dl:text>
  <dl:text key="cmdsynopsis-default-sepchar"> </dl:text>

</l:locale>
